ledgercli/__init__.py
ledgercli/bankinterface.py
ledgercli/cli.py
ledgercli/main.py
ledgercli/py.typed
ledger_cli-0.1.4.dist-info/LICENSE
ledger_cli-0.1.4.dist-info/METADATA
ledger_cli-0.1.4.dist-info/WHEEL
ledger_cli-0.1.4.dist-info/entry_points.txt
ledger_cli-0.1.4.dist-info/RECORD
