Metadata-Version: 2.1
Name: ledger-cli
Version: 0.1.4
Summary: ledger-cli
Home-page: https://github.com/tilschuenemann/ledger-cli
License: MIT
Author: Til Schünemann
Author-email: til.schuenemann@mailbox.org
Requires-Python: >=3.11,<4.0
Classifier: Development Status :: 3 - Alpha
Classifier: License :: OSI Approved :: MIT License
Classifier: Programming Language :: Python :: 3
Classifier: Programming Language :: Python :: 3.11
Requires-Dist: click (>=8.0.1)
Requires-Dist: numpy (>=1.23.5,<2.0.0)
Requires-Dist: pandas (>=2.0.3,<3.0.0)
Project-URL: Changelog, https://github.com/tilschuenemann/ledger-cli/releases
Project-URL: Documentation, https://ledger-cli.readthedocs.io
Project-URL: Repository, https://github.com/tilschuenemann/ledger-cli
